[
  {
    "id": "max-01",
    "nom": "Max",
    "espece": "Chien",
    "race": "Labrador croisé",
    "naissance": 2021,
    "sexe": "Mâle",
    "departement": "95 - Val d'Oise",
    "localisation": "Refuge",
    "statut": "Disponible",
    "description": "Max est un grand chien affectueux et joueur. Il adore les balades, les jeux de balle et les câlins sur le canapé. Sociable avec les personnes qu'il connaît, il cherche une famille qui pourra lui consacrer du temps et de l'attention. Une maison avec jardin serait idéale pour lui.",
    "entente_chiens": true,
    "entente_chats": false,
    "entente_enfants": true,
    "vaccine": true,
    "sterilise": false,
    "identifie": true,
    "participation_frais": 200,
    "association_nom": "Domaine de Fuego",
    "association_ville": "Val d'Oise (95)",
    "photos": [
      "https://images.unsplash.com/photo-1587300003388-59208cc962cb?w=600&q=80"
    ],
    "video_youtube": ""
  },
  {
    "id": "luna-02",
    "nom": "Luna",
    "espece": "Chat",
    "race": "Européenne",
    "naissance": 2023,
    "sexe": "Femelle",
    "departement": "95 - Val d'Oise",
    "localisation": "Famille d'accueil",
    "statut": "Archivé",
    "description": "Luna est une jeune chatte vive et curieuse. Elle est joueuse, câline quand elle le décide, et s'adapte facilement à un nouvel environnement. Elle sera parfaite pour une famille calme ou une personne seule souhaitant une compagnie douce et indépendante.",
    "entente_chiens": false,
    "entente_chats": true,
    "entente_enfants": true,
    "vaccine": true,
    "sterilise": true,
    "identifie": true,
    "participation_frais": 120,
    "association_nom": "Domaine de Fuego",
    "association_ville": "Val d'Oise (95)",
    "photos": [
      "https://images.unsplash.com/photo-1514888286974-6c03e2ca1dba?w=600&q=80"
    ],
    "video_youtube": ""
  },
  {
    "id": "oscar-03",
    "nom": "Oscar",
    "espece": "Chien",
    "race": "Beagle",
    "naissance": 2016,
    "sexe": "Mâle",
    "departement": "95 - Val d'Oise",
    "localisation": "Famille d'accueil",
    "statut": "Archivé",
    "description": "Oscar est un beagle senior plein de sérénité. Il a passé les années de son exubérance et cherche maintenant un foyer tranquille pour profiter de sa retraite. Il s'entend bien avec les enfants calmes et les autres chiens. Parfait pour une famille posée qui apprécie les promenades quotidiennes.",
    "entente_chiens": true,
    "entente_chats": false,
    "entente_enfants": true,
    "vaccine": true,
    "sterilise": true,
    "identifie": true,
    "participation_frais": 150,
    "association_nom": "Domaine de Fuego",
    "association_ville": "Val d'Oise (95)",
    "photos": [
      "https://images.unsplash.com/photo-1505628346881-b72b27e84530?w=600&q=80"
    ],
    "video_youtube": ""
  },
  {
    "id": "bella-04",
    "nom": "Bella",
    "espece": "Chat",
    "race": "Chartreux croisé",
    "naissance": 2020,
    "sexe": "Femelle",
    "departement": "95 - Val d'Oise",
    "localisation": "Refuge",
    "statut": "Archivé",
    "description": "Bella est une chatte au pelage gris doux et au caractère attachant. Elle est affectueuse avec les personnes qu'elle connaît et adore les séances de câlins le soir. Elle préfère être l'unique animal du foyer. Actuellement réservée — contactez-nous pour la liste d'attente.",
    "entente_chiens": false,
    "entente_chats": false,
    "entente_enfants": true,
    "vaccine": true,
    "sterilise": true,
    "identifie": true,
    "participation_frais": 130,
    "association_nom": "Domaine de Fuego",
    "association_ville": "Val d'Oise (95)",
    "photos": [
      "https://images.unsplash.com/photo-1495360010541-f48722b34f7d?w=600&q=80"
    ],
    "video_youtube": ""
  }
]